odoo10_addon_website_sale_commission_lead_geo_assign-10.0.1.0.0.99.dev10-py3.8-nspkg.pth
odoo/addons/website_sale_commission_lead_geo_assign/README.rst
odoo/addons/website_sale_commission_lead_geo_assign/__init__.py
odoo/addons/website_sale_commission_lead_geo_assign/__manifest__.py
odoo/addons/website_sale_commission_lead_geo_assign/data/data.xml
odoo/addons/website_sale_commission_lead_geo_assign/i18n/it.po
odoo/addons/website_sale_commission_lead_geo_assign/i18n/website_sale_commission_lead_geo_assign.pot
odoo/addons/website_sale_commission_lead_geo_assign/models/__init__.py
odoo/addons/website_sale_commission_lead_geo_assign/models/crm.py
odoo/addons/website_sale_commission_lead_geo_assign/readme/DESCRIPTION.rst
odoo/addons/website_sale_commission_lead_geo_assign/readme/USAGE.rst
odoo/addons/website_sale_commission_lead_geo_assign/static/description/icon.png
odoo/addons/website_sale_commission_lead_geo_assign/static/description/index.html
odoo/addons/website_sale_commission_lead_geo_assign/tests/__init__.py
odoo/addons/website_sale_commission_lead_geo_assign/tests/test_lead_geo_assign.py
odoo/addons/website_sale_commission_lead_geo_assign/wizards/__init__.py
odoo/addons/website_sale_commission_lead_geo_assign/wizards/wizard_geo_assign_lead.py
odoo/addons/website_sale_commission_lead_geo_assign/wizards/wizard_geo_assign_lead_view.xml
odoo10_addon_website_sale_commission_lead_geo_assign-10.0.1.0.0.99.dev10.dist-info/METADATA
odoo10_addon_website_sale_commission_lead_geo_assign-10.0.1.0.0.99.dev10.dist-info/WHEEL
odoo10_addon_website_sale_commission_lead_geo_assign-10.0.1.0.0.99.dev10.dist-info/namespace_packages.txt
odoo10_addon_website_sale_commission_lead_geo_assign-10.0.1.0.0.99.dev10.dist-info/top_level.txt
odoo10_addon_website_sale_commission_lead_geo_assign-10.0.1.0.0.99.dev10.dist-info/RECORD
