Metadata-Version: 2.1
Name: odoo10-addon-website-sale-commission-lead-geo-assign
Version: 10.0.1.0.0.99.dev10
Summary: Assign agents to leads according to their location
Home-page: https://github.com/OCA/commission/tree/10.0/website_sale_commission_lead_geo_assign
Author: Agile Business Group, Odoo Community Association (OCA)
Author-email: support@odoo-community.org
License: AGPL-3
Platform: UNKNOWN
Classifier: Programming Language :: Python
Classifier: Framework :: Odoo
Classifier: Framework :: Odoo :: 10.0
Classifier: License :: OSI Approved :: GNU Affero General Public License v3
Classifier: Development Status :: 4 - Beta
Requires-Python: ~=2.7
Requires-Dist: odoo10-addon-sale-commission-geo-assign
Requires-Dist: odoo <10.1dev,>=10.0
